Lab2_Haihan_Ref_Code/Hardware/Design_Source/Shifter.v
module Shifter(
    input [1:0] Sh,
    input [4:0] Shamt5,
    input [31:0] ShIn,
    
    output [31:0] ShOut
);

    // always @* begin
    //     case(Sh)
    //         2'b00: ShOut = {ShIn[(31-Shamt5):0], {Shamt5{1'b0}}};
    //         2'b01: ShOut = {{Shamt5{1'b0}}, ShIn[31:Shamt5]};
    //         2'b10: ShOut = {{Shamt5{ShIn[31]}}, ShIn[31:Shamt5]};
    //         2'b11: ShOut = {ShIn[Shamt5-1:0], ShIn[31:Shamt5]};
    //     endcase
    // end

    reg [31:0] ShMid [4:0];

    always @* begin
        case(Sh)
            2'b00: begin
                ShMid[0] = (Shamt5[4]) ? {ShIn[15:0], {16{1'b0}}} : ShIn;
                ShMid[1] = (Shamt5[3]) ? {ShMid[0][23:0], {8{1'b0}}} : ShMid[0];
                ShMid[2] = (Shamt5[2]) ? {ShMid[1][27:0], {4{1'b0}}} : ShMid[1];
                ShMid[3] = (Shamt5[1]) ? {ShMid[2][29:0], {2{1'b0}}} : ShMid[2];
                ShMid[4] = (Shamt5[0]) ? {ShMid[3][30:0], 1'b0     } : ShMid[3];            
            end
            2'b01: begin
                ShMid[0] = (Shamt5[4]) ? {{16{1'b0}}, ShIn[31:16]} : ShIn;
                ShMid[1] = (Shamt5[3]) ? {{8{1'b0}}, ShMid[0][31:8]} : ShMid[0];
                ShMid[2] = (Shamt5[2]) ? {{4{1'b0}}, ShMid[1][31:4]} : ShMid[1];
                ShMid[3] = (Shamt5[1]) ? {{2{1'b0}}, ShMid[2][31:2]} : ShMid[2];
                ShMid[4] = (Shamt5[0]) ? {  {1'b0} , ShMid[3][31:1]} : ShMid[3];            
            end
            2'b10: begin
                ShMid[0] = (Shamt5[4]) ? {{16{ShIn[31]}}, ShIn[31:16]} : ShIn;
                ShMid[1] = (Shamt5[3]) ? {{8{ShIn[31]}}, ShMid[0][31:8]} : ShMid[0];
                ShMid[2] = (Shamt5[2]) ? {{4{ShIn[31]}}, ShMid[1][31:4]} : ShMid[1];
                ShMid[3] = (Shamt5[1]) ? {{2{ShIn[31]}}, ShMid[2][31:2]} : ShMid[2];
                ShMid[4] = (Shamt5[0]) ? {  {ShIn[31]} , ShMid[3][31:1]} : ShMid[3];             
            end
            2'b11: begin
                ShMid[0] = (Shamt5[4]) ? {ShIn[15:0], ShIn[31:16]} : ShIn;
                ShMid[1] = (Shamt5[3]) ? {ShMid[0][7:0], ShMid[0][31:8]} : ShMid[0];
                ShMid[2] = (Shamt5[2]) ? {ShMid[1][3:0], ShMid[1][31:4]} : ShMid[1];
                ShMid[3] = (Shamt5[1]) ? {ShMid[2][1:0], ShMid[2][31:2]} : ShMid[2];
                ShMid[4]  = (Shamt5[0]) ? {ShMid[3][0]  , ShMid[3][31:1]} : ShMid[3];         
            end
        endcase 
    end

    assign ShOut = ShMid[4];

    /*
        LSL 00
        LSR 01
        ASR 10
        ROR 11
    */
endmodule

YuhangW_Final_Proj/Hardware/Simulation_Source/Shifter_tb.v
`timescale 1ns/1ps

module Shifter_tb;

    reg [1:0] Sh;
    reg [4:0] Shamt5;
    reg [31:0] ShIn;
    
    wire [31:0] ShOut;
    
    Shifter u_Shifter(
        .Sh     ( Sh     ),
        .Shamt5 ( Shamt5 ),
        .ShIn   ( ShIn   ),
        .ShOut  ( ShOut  )
    );

    integer out_shift;

    initial begin
         // store the simulation output as a Value Change Dump (VCD) file
        $dumpfile("Simulation_Source/shifter.vcd");
        // store everything at the current level and below
        $dumpvars(0, Shifter_tb);

        ShIn = 32'h2914AB4E; Shamt5 = 0; Sh = 0;
        
        #50 Sh = 1;
        #50 Sh = 2;
        #50 Sh = 3;

        #50 Shamt5 = 1; Sh = 0;  out_shift = ShIn << Shamt5;
        #50 Sh = 1; out_shift = ShIn >> Shamt5;
        #50 Sh = 2; out_shift = ShIn >>> Shamt5;
        #50 Sh = 3; out_shift = (ShIn >> Shamt5) + (ShIn << (32-Shamt5));

        #50 Shamt5 = 2; Sh = 0;  out_shift = ShIn << Shamt5;
        #50 Sh = 1; out_shift = ShIn >> Shamt5;
        #50 Sh = 2; out_shift = ShIn >>> Shamt5;
        #50 Sh = 3; out_shift = (ShIn >> Shamt5) + (ShIn << (32-Shamt5));

        #50 Shamt5 = 3; Sh = 0;  out_shift = ShIn << Shamt5;
        #50 Sh = 1; out_shift = ShIn >> Shamt5;
        #50 Sh = 2; out_shift = ShIn >>> Shamt5;
        #50 Sh = 3; out_shift = (ShIn >> Shamt5) + (ShIn << (32-Shamt5));

        #50 Shamt5 = 7; Sh = 0;  out_shift = ShIn << Shamt5;
        #50 Sh = 1; out_shift = ShIn >> Shamt5;
        #50 Sh = 2; out_shift = ShIn >>> Shamt5;
        #50 Sh = 3; out_shift = (ShIn >> Shamt5) + (ShIn << (32-Shamt5));

        #50 Shamt5 = 15; Sh = 0;  out_shift = ShIn << Shamt5;
        #50 Sh = 1; out_shift = ShIn >> Shamt5;
        #50 Sh = 2; out_shift = ShIn >>> Shamt5;
        #50 Sh = 3; out_shift = (ShIn >> Shamt5) + (ShIn << (32-Shamt5));

        #50 Shamt5 = 31; Sh = 0;  out_shift = ShIn << Shamt5;
        #50 Sh = 1; out_shift = ShIn >> Shamt5;
        #50 Sh = 2; out_shift = ShIn >>> Shamt5;
        #50 Sh = 3; out_shift = (ShIn >> Shamt5) + (ShIn << (32-Shamt5));

        #100 $finish;
    end

endmodule

YuhangW_Final_Proj/Hardware/Simulation_Source/shifter.vcd
$date
	Wed Nov 01 21:53:12 2023
$end
$version
	Icarus Verilog
$end
$timescale
	1ps
$end
$scope module Shifter_tb $end
$var wire 32 ! ShOut [31:0] $end
$var reg 2 " Sh [1:0] $end
$var reg 32 # ShIn [31:0] $end
$var reg 5 $ Shamt5 [4:0] $end
$var integer 32 % out_shift [31:0] $end
$scope module u_Shifter $end
$var wire 2 & Sh [1:0] $end
$var wire 32 ' ShIn [31:0] $end
$var wire 32 ( ShOut [31:0] $end
$var wire 5 ) Shamt5 [4:0] $end
$upscope $end
$upscope $end
$enddefinitions $end
$comment Show the parameter values. $end
$dumpall
$end
#0
$dumpvars
b0 )
b101001000101001010101101001110 (
b101001000101001010101101001110 '
b0 &
bx %
b0 $
b101001000101001010101101001110 #
b0 "
b101001000101001010101101001110 !
$end
#50000
b1 "
b1 &
#100000
b10 "
b10 &
#150000
b11 "
b11 &
#200000
b1010010001010010101011010011100 !
b1010010001010010101011010011100 (
b1010010001010010101011010011100 %
b0 "
b0 &
b1 $
b1 )
#250000
b10100100010100101010110100111 !
b10100100010100101010110100111 (
b10100100010100101010110100111 %
b1 "
b1 &
#300000
b10 "
b10 &
#350000
b11 "
b11 &
#400000
b10100100010100101010110100111000 !
b10100100010100101010110100111000 (
b10100100010100101010110100111000 %
b0 "
b0 &
b10 $
b10 )
#450000
b1010010001010010101011010011 !
b1010010001010010101011010011 (
b1010010001010010101011010011 %
b1 "
b1 &
#500000
b10 "
b10 &
#550000
b10001010010001010010101011010011 !
b10001010010001010010101011010011 (
b10001010010001010010101011010011 %
b11 "
b11 &
#600000
b1001000101001010101101001110000 !
b1001000101001010101101001110000 (
b1001000101001010101101001110000 %
b0 "
b0 &
b11 $
b11 )
#650000
b101001000101001010101101001 !
b101001000101001010101101001 (
b101001000101001010101101001 %
b1 "
b1 &
#700000
b10 "
b10 &
#750000
b11000101001000101001010101101001 !
b11000101001000101001010101101001 (
b11000101001000101001010101101001 %
b11 "
b11 &
#800000
b10001010010101011010011100000000 !
b10001010010101011010011100000000 (
b10001010010101011010011100000000 %
b0 "
b0 &
b111 $
b111 )
#850000
b10100100010100101010110 !
b10100100010100101010110 (
b10100100010100101010110 %
b1 "
b1 &
#900000
b10 "
b10 &
#950000
b10011100010100100010100101010110 !
b10011100010100100010100101010110 (
b10011100010100100010100101010110 %
b11 "
b11 &
#1000000
b1010101101001110000000000000000 !
b1010101101001110000000000000000 (
b1010101101001110000000000000000 %
b0 "
b0 &
b1111 $
b1111 )
#1050000
b101001000101001 !
b101001000101001 (
b101001000101001 %
b1 "
b1 &
#1100000
b10 "
b10 &
#1150000
b1010110100111000101001000101001 !
b1010110100111000101001000101001 (
b1010110100111000101001000101001 %
b11 "
b11 &
#1200000
b0 !
b0 (
b0 %
b0 "
b0 &
b11111 $
b11111 )
#1250000
b1 "
b1 &
#1300000
b10 "
b10 &
#1350000
b1010010001010010101011010011100 !
b1010010001010010101011010011100 (
b1010010001010010101011010011100 %
b11 "
b11 &
