YuhangW_Final_Proj/Hardware/Design_Source/ProgramCounter.v
module ProgramCounter(
    input CLK,
    input Reset,
    input PCSrc,
    input [31:0] Result,
    
    output reg [31:0] PC,
    output [31:0] PC_Plus_4
); 

//fill your Verilog code here

    always @(posedge CLK or posedge Reset) begin
        if(Reset) PC <= 0;
        else PC <= (PCSrc) ? Result : PC_Plus_4;
    end

    assign PC_Plus_4 = PC + 32'd4; 

endmodule

YuhangW_Final_Proj/Hardware/Simulation_Source/PC_tb.v
`timescale 1ns/1ps

module PC_tb;

    reg CLK, Reset, PCSrc;
    reg [31:0] Result;
    wire [31:0] PC, PC_Plus_4;

    ProgramCounter u_ProgramCounter(
        .CLK    ( CLK    ),
        .Reset  ( Reset  ),
        .PCSrc  ( PCSrc  ),
        .Result ( Result ),
        .PC     ( PC     ),
        .PC_Plus_4  ( PC_Plus_4  )
    );

    always begin
        #5 CLK = ~CLK;
    end

    initial begin
         // store the simulation output as a Value Change Dump (VCD) file
        $dumpfile("Simulation_Source/PC.vcd");
        // store everything at the current level and below
        $dumpvars(0, PC_tb);

        CLK = 0; Reset = 1; PCSrc = 0;
        Result = 32'h2914AB4E; 

        #20 Reset = 0;
        
        #100 PCSrc = 1;
        #10 PCSrc = 0;

        #100 $finish;
    end

endmodule

1_Baseline_CPU/Hardware/Simulation_Source/PC.vcd
$date
	Tue Oct 24 09:26:39 2023
$end
$version
	Icarus Verilog
$end
$timescale
	1ps
$end
$scope module PC_tb $end
$var wire 32 ! PC_Plus_4 [31:0] $end
$var wire 32 " PC [31:0] $end
$var reg 1 # CLK $end
$var reg 1 $ PCSrc $end
$var reg 1 % Reset $end
$var reg 32 & Result [31:0] $end
$scope module u_ProgramCounter $end
$var wire 1 # CLK $end
$var wire 1 $ PCSrc $end
$var wire 1 % Reset $end
$var wire 32 ' Result [31:0] $end
$var wire 32 ( PC_Plus_4 [31:0] $end
$var reg 32 ) PC [31:0] $end
$upscope $end
$upscope $end
$enddefinitions $end
$comment Show the parameter values. $end
$dumpall
$end
#0
$dumpvars
b0 )
b100 (
b101001000101001010101101001110 '
b101001000101001010101101001110 &
1%
0$
0#
b0 "
b100 !
$end
#5000
1#
#10000
0#
#15000
1#
#20000
0#
0%
#25000
b1000 !
b1000 (
b100 "
b100 )
1#
#30000
0#
#35000
b1100 !
b1100 (
b1000 "
b1000 )
1#
#40000
0#
#45000
b10000 !
b10000 (
b1100 "
b1100 )
1#
#50000
0#
#55000
b10100 !
b10100 (
b10000 "
b10000 )
1#
#60000
0#
#65000
b11000 !
b11000 (
b10100 "
b10100 )
1#
#70000
0#
#75000
b11100 !
b11100 (
b11000 "
b11000 )
1#
#80000
0#
#85000
b100000 !
b100000 (
b11100 "
b11100 )
1#
#90000
0#
#95000
b100100 !
b100100 (
b100000 "
b100000 )
1#
#100000
0#
#105000
b101000 !
b101000 (
b100100 "
b100100 )
1#
#110000
0#
#115000
b101100 !
b101100 (
b101000 "
b101000 )
1#
#120000
0#
1$
#125000
b101001000101001010101101010010 !
b101001000101001010101101010010 (
b101001000101001010101101001110 "
b101001000101001010101101001110 )
1#
#130000
0#
0$
#135000
b101001000101001010101101010110 !
b101001000101001010101101010110 (
b101001000101001010101101010010 "
b101001000101001010101101010010 )
1#
#140000
0#
#145000
b101001000101001010101101011010 !
b101001000101001010101101011010 (
b101001000101001010101101010110 "
b101001000101001010101101010110 )
1#
#150000
0#
#155000
b101001000101001010101101011110 !
b101001000101001010101101011110 (
b101001000101001010101101011010 "
b101001000101001010101101011010 )
1#
#160000
0#
#165000
b101001000101001010101101100010 !
b101001000101001010101101100010 (
b101001000101001010101101011110 "
b101001000101001010101101011110 )
1#
#170000
0#
#175000
b101001000101001010101101100110 !
b101001000101001010101101100110 (
b101001000101001010101101100010 "
b101001000101001010101101100010 )
1#
#180000
0#
#185000
b101001000101001010101101101010 !
b101001000101001010101101101010 (
b101001000101001010101101100110 "
b101001000101001010101101100110 )
1#
#190000
0#
#195000
b101001000101001010101101101110 !
b101001000101001010101101101110 (
b101001000101001010101101101010 "
b101001000101001010101101101010 )
1#
#200000
0#
#205000
b101001000101001010101101110010 !
b101001000101001010101101110010 (
b101001000101001010101101101110 "
b101001000101001010101101101110 )
1#
#210000
0#
#215000
b101001000101001010101101110110 !
b101001000101001010101101110110 (
b101001000101001010101101110010 "
b101001000101001010101101110010 )
1#
#220000
0#
#225000
b101001000101001010101101111010 !
b101001000101001010101101111010 (
b101001000101001010101101110110 "
b101001000101001010101101110110 )
1#
